{"options":{"validationAction":"error","validator":{"$jsonSchema":{"bsonType":"object","required":["idString","bookingGuest","checkIn","checkOut","roomType_id","totalCost","guestList"],"properties":{"totalCost":{"bsonType":"decimal"},"idString":{"bsonType":"string"},"bookingGuest":{"bsonType":"object"},"room_id":{"bsonType":["objectId","string"]},"checkIn":{"bsonType":"date"},"checkOut":{"bsonType":"date"},"roomType_id":{"bsonType":"objectId"},"guestList":{"minItems":{"$numberInt":"0"},"items":{"bsonType":"object"},"bsonType":["array"]}}}},"validationLevel":"off"},"indexes":[{"v":{"$numberInt":"2"},"key":{"_id":{"$numberInt":"1"}},"name":"_id_"},{"v":{"$numberInt":"2"},"key":{"checkIn":{"$numberInt":"1"}},"name":"checkIn_1","background":false},{"v":{"$numberInt":"2"},"key":{"checkOut":{"$numberInt":"1"}},"name":"checkOut_1","background":false},{"v":{"$numberInt":"2"},"key":{"room_id":{"$numberInt":"1"}},"name":"room_id_1","background":false},{"v":{"$numberInt":"2"},"key":{"roomType_id":{"$numberInt":"1"}},"name":"roomType_id_1","background":false},{"v":{"$numberInt":"2"},"key":{"_fts":"text","_ftsx":{"$numberInt":"1"}},"name":"$**_text","weights":{"$**":{"$numberInt":"1"}},"default_language":"english","language_override":"language","textIndexVersion":{"$numberInt":"3"}}],"uuid":"b60e842a02094021bad4fba8b543ee30","collectionName":"reservations"}